leaderboard/__init__.py
leaderboard/ext_plot.py
leaderboard/leaderboard_gen.py
leaderboard/rtd_build_trigger.py
leaderboard/utils.py
pyhealth/__init__.py
pyhealth/tokenizer.py
pyhealth/trainer.py
pyhealth/utils.py
pyhealth/calib/__init__.py
pyhealth/calib/base_classes.py
pyhealth/calib/utils.py
pyhealth/calib/calibration/__init__.py
pyhealth/calib/calibration/dircal.py
pyhealth/calib/calibration/hb.py
pyhealth/calib/calibration/temperature_scale.py
pyhealth/calib/calibration/kcal/__init__.py
pyhealth/calib/calibration/kcal/bw.py
pyhealth/calib/calibration/kcal/embed_data.py
pyhealth/calib/calibration/kcal/kde.py
pyhealth/calib/predictionset/__init__.py
pyhealth/calib/predictionset/label.py
pyhealth/calib/predictionset/favmac/__init__.py
pyhealth/calib/predictionset/favmac/core.py
pyhealth/calib/predictionset/favmac/quantiletree.py
pyhealth/calib/predictionset/scrib/__init__.py
pyhealth/calib/predictionset/scrib/quicksearch.py
pyhealth/data/__init__.py
pyhealth/data/data.py
pyhealth/datasets/TUAB.py
pyhealth/datasets/TUEV.py
pyhealth/datasets/__init__.py
pyhealth/datasets/base_dataset_v2.py
pyhealth/datasets/base_ehr_dataset.py
pyhealth/datasets/base_signal_dataset.py
pyhealth/datasets/cardiology.py
pyhealth/datasets/covid19_cxr.py
pyhealth/datasets/eicu.py
pyhealth/datasets/isruc.py
pyhealth/datasets/mimic3.py
pyhealth/datasets/mimic4.py
pyhealth/datasets/mimicextract.py
pyhealth/datasets/omop.py
pyhealth/datasets/sample_dataset.py
pyhealth/datasets/sample_dataset_v2.py
pyhealth/datasets/shhs.py
pyhealth/datasets/sleepedf.py
pyhealth/datasets/splitter.py
pyhealth/datasets/tuab.py
pyhealth/datasets/tuev.py
pyhealth/datasets/utils.py
pyhealth/datasets/featurizers/__init__.py
pyhealth/datasets/featurizers/image.py
pyhealth/datasets/featurizers/value.py
pyhealth/interpret/__init__.py
pyhealth/interpret/methods/__init__.py
pyhealth/interpret/methods/chefer.py
pyhealth/medcode/__init__.py
pyhealth/medcode/cross_map.py
pyhealth/medcode/inner_map.py
pyhealth-1.1.6.dist-info/METADATA
pyhealth-1.1.6.dist-info/WHEEL
pyhealth-1.1.6.dist-info/top_level.txt
pyhealth-1.1.6.dist-info/RECORD
