Metadata-Version: 2.1
Name: pyhealth
Version: 1.1.6
Summary: A Python library for healthcare AI
Home-page: https://github.com/sunlabuiuc/pyhealth
Author: Chaoqi Yang, Zhenbang Wu, Patrick Jiang, Zhen Lin, Benjamin Danek, Junyi Gao, Jimeng Sun
Author-email: chaoqiy2@illinois.edu
Keywords: heathcare AI,healthcare,electronic health records,EHRs,machine learning,data mining,neural networks,deep learning
Classifier: Development Status :: 3 - Alpha
Classifier: Intended Audience :: Education
Classifier: Intended Audience :: Financial and Insurance Industry
Classifier: Intended Audience :: Science/Research
Classifier: Intended Audience :: Developers
Classifier: Intended Audience :: Information Technology
Classifier: License :: OSI Approved :: BSD License
Classifier: Programming Language :: Python :: 3.8
Requires-Dist: torch >=1.8.0
Requires-Dist: torchvision >=0.9.0
Requires-Dist: rdkit >=2022.03.4
Requires-Dist: scikit-learn >=0.24.2
Requires-Dist: networkx >=2.6.3
Requires-Dist: pandas <2,>=1.3.2
Requires-Dist: pandarallel >=1.5.3
Requires-Dist: mne >=1.0.3
Requires-Dist: urllib3 <=1.26.15
Requires-Dist: numpy
Requires-Dist: tqdm
